README.md
setup.py
arelle/Cntlr.py
arelle/DisclosureSystem.py
arelle/FileSource.py
arelle/FormulaConsisAsser.py
arelle/FormulaEvaluator.py
arelle/FunctionCustom.py
arelle/FunctionFn.py
arelle/FunctionIxt.py
arelle/FunctionUtil.py
arelle/FunctionXfi.py
arelle/FunctionXs.py
arelle/HashUtil.py
arelle/HtmlUtil.py
arelle/InstanceAspectsEvaluator.py
arelle/LeiUtil.py
arelle/Locale.py
arelle/ModelDocument.py
arelle/ModelDtsObject.py
arelle/ModelFormulaObject.py
arelle/ModelInstanceObject.py
arelle/ModelManager.py
arelle/ModelObject.py
arelle/ModelObjectFactory.py
arelle/ModelRelationshipSet.py
arelle/ModelRenderingObject.py
arelle/ModelRssItem.py
arelle/ModelRssObject.py
arelle/ModelTestcaseObject.py
arelle/ModelValue.py
arelle/ModelVersObject.py
arelle/ModelVersReport.py
arelle/ModelXbrl.py
arelle/PackageManager.py
arelle/PluginManager.py
arelle/PrototypeDtsObject.py
arelle/PrototypeInstanceObject.py
arelle/PythonUtil.py
arelle/RenderingEvaluator.py
arelle/RenderingResolver.py
arelle/TableStructure.py
arelle/TestArelle.py
arelle/TkTableWrapper.py
arelle/UITkTable.py
arelle/UiUtil.py
arelle/Updater.py
arelle/UrlUtil.py
arelle/Validate.py
arelle/ValidateFiling.py
arelle/ValidateFilingDTS.py
arelle/ValidateFilingDimensions.py
arelle/ValidateFilingText.py
arelle/ValidateFormula.py
arelle/ValidateHmrc.py
arelle/ValidateInfoset.py
arelle/ValidateUtr.py
arelle/ValidateVersReport.py
arelle/ValidateXbrl.py
arelle/ValidateXbrlCalcs.py
arelle/ValidateXbrlDTS.py
arelle/ValidateXbrlDimensions.py
arelle/Version.py
arelle/ViewFile.py
arelle/ViewFileConcepts.py
arelle/ViewFileDTS.py
arelle/ViewFileFactList.py
arelle/ViewFileFactTable.py
arelle/ViewFileFormulae.py
arelle/ViewFileRelationshipSet.py
arelle/ViewFileRenderedGrid.py
arelle/ViewFileRoleTypes.py
arelle/ViewFileRssFeed.py
arelle/ViewFileTests.py
arelle/ViewUtil.py
arelle/ViewUtilFormulae.py
arelle/WatchRss.py
arelle/WebCache.py
arelle/XPathContext.py
arelle/XPathParser.py
arelle/XbrlConst.py
arelle/XbrlUtil.py
arelle.egg-info/PKG-INFO
arelle.egg-info/SOURCES.txt
arelle.egg-info/dependency_links.txt
arelle.egg-info/top_level.txt
